{
  "gitSyncId": "6710f7c4cf7aa326b25f7ad5_833c6f29-5418-4dcc-a1e6-175ec642e125",
  "unpublishedPage": {
    "layouts": [
      {
        "dsl": {
          "backgroundColor": "none",
          "bottomRow": 500,
          "canExtend": true,
          "containerStyle": "none",
          "detachFromLayout": true,
          "dynamicBindingPathList": [],
          "dynamicTriggerPathList": [],
          "leftColumn": 0,
          "minHeight": 1292,
          "parentColumnSpace": 1,
          "parentRowSpace": 1,
          "rightColumn": 4896,
          "snapColumns": 64,
          "snapRows": 124,
          "topRow": 0,
          "type": "CANVAS_WIDGET",
          "version": 90,
          "widgetId": "0",
          "widgetName": "MainContainer"
        }
      }
    ],
    "name": "Page1",
    "slug": "page1"
  }
}